moonbase/__init__.py
moonbase/_base_client.py
moonbase/_client.py
moonbase/_compat.py
moonbase/_constants.py
moonbase/_exceptions.py
moonbase/_files.py
moonbase/_models.py
moonbase/_qs.py
moonbase/_resource.py
moonbase/_response.py
moonbase/_streaming.py
moonbase/_types.py
moonbase/_version.py
moonbase/pagination.py
moonbase/py.typed
moonbase/_utils/__init__.py
moonbase/_utils/_compat.py
moonbase/_utils/_datetime_parse.py
moonbase/_utils/_logs.py
moonbase/_utils/_proxy.py
moonbase/_utils/_reflection.py
moonbase/_utils/_resources_proxy.py
moonbase/_utils/_streams.py
moonbase/_utils/_sync.py
moonbase/_utils/_transform.py
moonbase/_utils/_typing.py
moonbase/_utils/_utils.py
moonbase/lib/.keep
moonbase/resources/__init__.py
moonbase/resources/activities.py
moonbase/resources/calls.py
moonbase/resources/files.py
moonbase/resources/forms.py
moonbase/resources/inbox_conversations.py
moonbase/resources/inbox_messages.py
moonbase/resources/inboxes.py
moonbase/resources/meetings.py
moonbase/resources/notes.py
moonbase/resources/program_messages.py
moonbase/resources/program_templates.py
moonbase/resources/programs.py
moonbase/resources/tagsets.py
moonbase/resources/webhook_endpoints.py
moonbase/resources/collections/__init__.py
moonbase/resources/collections/collections.py
moonbase/resources/collections/fields.py
moonbase/resources/collections/items.py
moonbase/resources/views/__init__.py
moonbase/resources/views/items.py
moonbase/resources/views/views.py
moonbase/types/__init__.py
moonbase/types/activity.py
moonbase/types/activity_call_occurred.py
moonbase/types/activity_form_submitted.py
moonbase/types/activity_inbox_message_sent.py
moonbase/types/activity_item_created.py
moonbase/types/activity_item_mentioned.py
moonbase/types/activity_item_merged.py
moonbase/types/activity_list_params.py
moonbase/types/activity_meeting_held.py
moonbase/types/activity_meeting_scheduled.py
moonbase/types/activity_note_created.py
moonbase/types/activity_program_message_bounced.py
moonbase_sdk-0.1.0a5.dist-info/METADATA
moonbase_sdk-0.1.0a5.dist-info/WHEEL
moonbase_sdk-0.1.0a5.dist-info/licenses/LICENSE
moonbase_sdk-0.1.0a5.dist-info/RECORD
